py3dst/__init__.py
py3dst/__main__.py
py3dst/error_classes.py
py3dst/primitive_types.py
py3dst/tex3dst.py
py3dst/utils.py
py3dst-1.2.2.dist-info/LICENSE
py3dst-1.2.2.dist-info/METADATA
py3dst-1.2.2.dist-info/WHEEL
py3dst-1.2.2.dist-info/top_level.txt
py3dst-1.2.2.dist-info/RECORD
