Metadata-Version: 2.1
Name: py3dst
Version: 1.2.2
Summary: Python module to read/edit 3DST textures.
Author-email: STBrian <brichap100@gmail.com>
License:                     GNU GENERAL PUBLIC LICENSE
Project-URL: Homepage, https://github.com/STBrian/py3dst
Keywords: 3dst
Classifier: License :: OSI Approved :: GNU General Public License v3 (GPLv3)
Classifier: Programming Language :: Python
Classifier: Programming Language :: Python :: 3
Requires-Python: >=3.11
License-File: LICENSE
Requires-Dist: numpy>=1.26.0
Requires-Dist: pillow>=10.0.0
